{
  "product": {
    "id": "PROD-014-V02",
    "name": "Product 014 Variant 02",
    "base_product_id": "PROD-014",
    "root_subassembly": "SA-084",
    "revision": "B",
    "variant_of_revision": "B",
    "created_utc": "2025-12-24T14:07:02Z"
  },
  "bom_overrides": [
    {
      "op": "qty_delta",
      "parent_subassembly_id": "SA-084",
      "child_type": "subassembly",
      "child_id": "SA-003",
      "delta": 1
    },
    {
      "op": "qty_delta",
      "parent_subassembly_id": "SA-084",
      "child_type": "subassembly",
      "child_id": "SA-066",
      "delta": -1
    },
    {
      "op": "qty_delta",
      "parent_subassembly_id": "SA-021",
      "child_type": "subassembly",
      "child_id": "SA-015",
      "delta": 1
    },
    {
      "op": "qty_delta",
      "parent_subassembly_id": "SA-021",
      "child_type": "component",
      "child_id": "CMP-031",
      "delta": 1
    },
    {
      "op": "qty_delta",
      "parent_subassembly_id": "SA-067",
      "child_type": "subassembly",
      "child_id": "SA-063",
      "delta": 1
    },
    {
      "op": "qty_delta",
      "parent_subassembly_id": "SA-067",
      "child_type": "subassembly",
      "child_id": "SA-047",
      "delta": 2
    },
    {
      "op": "replace_child",
      "parent_subassembly_id": "SA-084",
      "old_child_type": "subassembly",
      "old_child_id": "SA-003",
      "new_child_type": "subassembly",
      "new_child_id": "SA-001",
      "new_qty": 2
    },
    {
      "op": "add_child",
      "parent_subassembly_id": "SA-084",
      "child_type": "component",
      "child_id": "CMP-008",
      "qty": 3
    }
  ]
}